<?xml version="1.0" encoding="UTF-8"?>
<Grar>
    <Parameters>
        <!-- LMS mode : AICC/SCORM -->
        <Mode>AICC</Mode>
        <!-- Module title -->
        <Title>SAMPLE ACTIVITY</Title>
        <!-- State of the local save -->
        <State>fr@1@0-0-0@3</State>
        <!-- Paths to the langages files -->
        <Languages file="lang.xml"/>
    </Parameters>
    <!-- List of static displays -->
    <Display>
        <Activity display="quizzDisplay.xml"/>
        <Activity display="cardsDisplay.xml"/>
        <Activity display="scannerDisplay.xml"/>
        <Activity display="folderDisplay.xml"/>
        <Ui display="ui/ui.xml"/>
    </Display>
    <!-- Structure of the application -->
    <Structure idObjective="">
        <Part id="0" name="trancheDeVie" type="dialog" file="tranche.xml" display="trancheDisplay.xml"/>
        <Part id="1" name="activities" type="" file="activities.xml" display="activitiesDisplay.xml"/>
        <Part id="2" name="bild" type="strip" file="strip.xml" display="stripDisplay.xml"/>
    </Structure>
</Grar>
